reclaimer/AUTHORS.TXT
reclaimer/CHANGELOG.MD
reclaimer/LICENSE
reclaimer/README.MD
reclaimer/__init__.py
reclaimer/common_descs.py
reclaimer/constants.py
reclaimer/data_extraction.py
reclaimer/enums.py
reclaimer/field_type_methods.py
reclaimer/field_types.py
reclaimer/generate_supyr_defs_from_xml.py
reclaimer/tag_definition_extractor.py
reclaimer/animation/__init__.py
reclaimer/animation/animation_compilation.py
reclaimer/animation/animation_compression.py
reclaimer/animation/animation_decompilation.py
reclaimer/animation/jma.py
reclaimer/animation/serialization.py
reclaimer/animation/structs.py
reclaimer/animation/util.py
reclaimer/bitmaps/__init__.py
reclaimer/bitmaps/bitmap_compilation.py
reclaimer/bitmaps/bitmap_decompilation.py
reclaimer/bitmaps/meter_image.py
reclaimer/bitmaps/p8_palette.py
reclaimer/bitmaps/p8_palette_halo
reclaimer/bitmaps/p8_palette_halo_diff_map
reclaimer/bitmaps/p8_palette_stubbs
reclaimer/bitmaps/p8_palette_stubbs_diff_map
reclaimer/h2/__init__.py
reclaimer/h2/common_descs.py
reclaimer/h2/constants.py
reclaimer/h2/enums.py
reclaimer/h2/field_type_methods.py
reclaimer/h2/field_types.py
reclaimer/h2/handler.py
reclaimer/h2/util.py
reclaimer/h2/defs/__init__.py
reclaimer/h2/defs/ant_.py
reclaimer/h2/defs/bitm.py
reclaimer/h2/defs/hsc_.py
reclaimer/h2/defs/pphy.py
reclaimer/h2/defs/shad.py
reclaimer/h2/defs/snd_.py
reclaimer/h2/defs/trak.py
reclaimer/h2/defs/ugh_.py
reclaimer/h2/defs/objs/__init__.py
reclaimer/h2/defs/objs/tag.py
reclaimer/h3/__init__.py
reclaimer/h3/common_descs.py
reclaimer/h3/constants.py
reclaimer/h3/enums.py
reclaimer/h3/field_type_methods.py
reclaimer/h3/field_types.py
reclaimer/h3/handler.py
reclaimer/h3/util.py
reclaimer/h3/defs/__init__.py
reclaimer/h3/defs/_fx_.py
reclaimer/h3/defs/adlg.py
reclaimer/h3/defs/ant_.py
reclaimer/h3/defs/beam.py
reclaimer/h3/defs/bipd.py
reclaimer/h3/defs/bitm.py
reclaimer/h3/defs/bkey.py
reclaimer/h3/defs/bloc.py
reclaimer/h3/defs/bmp3.py
reclaimer/h3/defs/bsdt.py
reclaimer-2.11.2.dist-info/AUTHORS.TXT
reclaimer-2.11.2.dist-info/LICENSE
reclaimer-2.11.2.dist-info/METADATA
reclaimer-2.11.2.dist-info/WHEEL
reclaimer-2.11.2.dist-info/top_level.txt
reclaimer-2.11.2.dist-info/RECORD
