Metadata-Version: 2.1
Name: reclaimer
Version: 2.11.2
Summary: A libray of SupyrStruct structures and objects for games built with the Blam engine
Home-page: https://github.com/Sigmmma/reclaimer
Author: Sigmmma
Author-email: MosesBobadilla@gmail.com
License: GPLv3
Project-URL: Source, https://github.com/Sigmmma/reclaimer
Project-URL: Funding, https://liberapay.com/MEK/
Keywords: reclaimer,halo
Platform: POSIX
Platform: Windows
Classifier: Development Status :: 4 - Beta
Classifier: Intended Audience :: End Users/Desktop
Classifier: License :: OSI Approved :: GNU General Public License v3 (GPLv3)
Classifier: Programming Language :: Python
Classifier: Programming Language :: Python :: 3
Classifier: Programming Language :: Python :: 3.5
Classifier: Programming Language :: Python :: 3.6
Classifier: Programming Language :: Python :: 3.7
Classifier: Programming Language :: Python :: 3.8
Classifier: Programming Language :: Python :: 3.9
Classifier: Programming Language :: Python :: 3 :: Only
Classifier: Programming Language :: C
Requires: supyr_struct
Requires: binilla
Requires: arbytmap
Provides: reclaimer
Requires-Python: >=3.5
Requires-Dist: supyr-struct (>=1.5.0)
Requires-Dist: binilla
Requires-Dist: arbytmap
